psquared_client/__init__.py
psquared_client/display.py
psquared_client/pp_cli.py
psquared_client/psquared.py
psquared_client/psquared_utils.py
psquared_client/py.typed
psquared_client/request_error.py
psquared_client/response_error.py
psquared_client/utils.py
psquared_client-3.2.1.dist-info/LICENSE.txt
psquared_client-3.2.1.dist-info/METADATA
psquared_client-3.2.1.dist-info/WHEEL
psquared_client-3.2.1.dist-info/entry_points.txt
psquared_client-3.2.1.dist-info/top_level.txt
psquared_client-3.2.1.dist-info/RECORD
